kyodo/__init__.py
kyodo/client.py
kyodo/main.py
kyodo/ws.py
kyodo/utils/__init__.py
kyodo/utils/device_id.py
kyodo/utils/exceptions.py
kyodo/utils/objects.py
kyodo/utils/signature.py
kyodo/utils/strtime.py
kyodo/utils/wrappers.py
py_kyodo-1.0.1.dist-info/METADATA
py_kyodo-1.0.1.dist-info/WHEEL
py_kyodo-1.0.1.dist-info/licenses/LICENSE
py_kyodo-1.0.1.dist-info/RECORD
