Metadata-Version: 2.4
Name: py.kyodo
Version: 1.0.1
Summary: Basic library to interract with Kyodo
Project-URL: Download, https://github.com/fedd20/py.kyodo.git
Project-URL: Homepage, https://github.com/fedd20/py.kyodo
Project-URL: Issues, https://github.com/fedd20/py.kyodo/issues
License-Expression: MIT
License-File: LICENSE
Keywords: fedd20,fedora,hexagon,imperialwool,kyodo,kyodo amino,kyodo app,py kyodo,py.kyodo,python kyodo
Classifier: Intended Audience :: Developers
Classifier: License :: OSI Approved :: MIT License
Classifier: Programming Language :: Python
Classifier: Programming Language :: Python :: 3 :: Only
Classifier: Programming Language :: Python :: 3.8
Classifier: Programming Language :: Python :: 3.9
Classifier: Programming Language :: Python :: 3.10
Classifier: Programming Language :: Python :: 3.11
Classifier: Programming Language :: Python :: 3.12
Classifier: Programming Language :: Python :: 3.13
Requires-Python: >=3.9
Requires-Dist: httpx>=0.28.1
Requires-Dist: orjson>=3.11.5
Requires-Dist: pyjwt>=2.10.1
Requires-Dist: websockets>=15.0.1
Provides-Extra: dev
Requires-Dist: build; extra == 'dev'
Requires-Dist: hatch; extra == 'dev'
Requires-Dist: twine; extra == 'dev'
Requires-Dist: wheel; extra == 'dev'
